MANIFEST.in
setup.py
directupload/__init__.py
directupload/admin.py
directupload/app_settings.py
directupload/models.py
directupload/urls.py
directupload/views.py
directupload/widgets.py
directupload/backends/__init__.py
directupload/backends/base.py
directupload/backends/djangoview.py
directupload/backends/s3.py
directupload/backends/utils.py
directupload/static/directupload/widget.js
directupload/static/directupload/js/jquery.fileupload-ip.js
directupload/static/directupload/js/jquery.fileupload-ui.js
directupload/static/directupload/js/jquery.fileupload.js
directupload/static/directupload/js/jquery.iframe-transport.js
directupload/static/directupload/js/locale.js
directupload/static/directupload/js/main.js
directupload/static/directupload/js/cors/jquery.postmessage-transport.js
directupload/static/directupload/js/cors/jquery.xdr-transport.js
directupload/static/directupload/js/vendor/jquery.ui.widget.js
directupload/templates/admin/includes/fieldset.html
directupload/templates/directupload/templatetags/head.html
directupload/templates/directupload/templatetags/render_file_widget.html
directupload/templatetags/__init__.py
directupload/templatetags/directupload_tags.py
django_directupload.egg-info/PKG-INFO
django_directupload.egg-info/SOURCES.txt
django_directupload.egg-info/dependency_links.txt
django_directupload.egg-info/top_level.txt