Metadata-Version: 1.0
Name: django-directupload
Version: 0.0.9
Summary: A Django application that offers direct uploading of files from your forms using Uploadify.
Home-page: https://github.com/cuker/django-directupload
Author: Jason Kraus
Author-email: jasonk@cukerinteractive.com
License: UNKNOWN
Platform: UNKNOWN
Classifier: Development Status :: 4 - Beta
Classifier: Environment :: Web Environment
Classifier: Framework :: Django
Classifier: Intended Audience :: Developers
Classifier: License :: OSI Approved :: BSD License
Classifier: Operating System :: OS Independent
Classifier: Programming Language :: Python
Classifier: Topic :: Utilities
